procspec/__init__.py
procspec/basic_procs.py
procspec/parse.py
procspec/proc_base.py
procspec/procs.py
procspec/scriber.py
procspec-0.0.4.dist-info/LICENSE
procspec-0.0.4.dist-info/METADATA
procspec-0.0.4.dist-info/WHEEL
procspec-0.0.4.dist-info/top_level.txt
procspec-0.0.4.dist-info/RECORD
