Metadata-Version: 2.1
Name: procspec
Version: 0.0.4
Summary: Library for simple and powerful YAML specification of computational tasks.
Home-page: https://github.com/supersergiy/procspec
Author: Sergiy Popovych
Author-email: sergiy.popovich@gmail.com
License: UNKNOWN
Platform: UNKNOWN
Requires-Dist: six
Requires-Dist: artificery
Requires-Dist: pyyaml
